mask_plugin.py
mkdocs_mask_plugin-0.1.dist-info/licenses/LICENSE
mkdocs_mask_plugin-0.1.dist-info/METADATA
mkdocs_mask_plugin-0.1.dist-info/WHEEL
mkdocs_mask_plugin-0.1.dist-info/entry_points.txt
mkdocs_mask_plugin-0.1.dist-info/top_level.txt
mkdocs_mask_plugin-0.1.dist-info/RECORD
