Metadata-Version: 2.4
Name: mkdocs-mask-plugin
Version: 0.1
Summary: A MkDocs plugin that adds a custom syntax to hide text behind a black box until hovered.
Author: eWloYW8
Author-email: 3171132517@qq.com
License: MIT
Classifier: Programming Language :: Python :: 3
Classifier: License :: Public Domain
Classifier: Operating System :: OS Independent
Requires-Python: >=3.6
License-File: LICENSE
Requires-Dist: mkdocs>=1.1
Requires-Dist: markdown
Dynamic: author
Dynamic: author-email
Dynamic: classifier
Dynamic: description
Dynamic: description-content-type
Dynamic: license
Dynamic: license-file
Dynamic: requires-dist
Dynamic: requires-python
Dynamic: summary
